colorspot
