Metadata-Version: 2.1
Name: colorspot
Version: 0.1.6
Summary: A colorful CLI DX cluster client with LotW integration
Home-page: https://git.qrz.is/clemens/colorspot
Author: Michael Clemens
Author-email: colorspot@qrz.is
License: UNKNOWN
Project-URL: Bug Tracker, https://git.qrz.is/clemens/colorspot/issues
Platform: UNKNOWN
Classifier: Programming Language :: Python :: 3
Classifier: License :: OSI Approved :: MIT License
Classifier: Operating System :: OS Independent
Requires-Python: >=3.6
